terminalpycolor/__init__.py
terminalpycolor/color.py
terminalpycolor-1.0.2.dist-info/LICENSE
terminalpycolor-1.0.2.dist-info/METADATA
terminalpycolor-1.0.2.dist-info/WHEEL
terminalpycolor-1.0.2.dist-info/top_level.txt
terminalpycolor-1.0.2.dist-info/RECORD
