Metadata-Version: 2.1
Name: terminalpycolor
Version: 1.0.2
Summary: A simple python library that can be used on designing your Terminal
Home-page: https://github.com/jiroawesome/terminalpycolor
Author: jiroawesome
License: UNKNOWN
Project-URL: Bug Tracker, https://github.com/jiroawesome/terminalpycolor/issues
Platform: UNKNOWN
Classifier: Programming Language :: Python :: 3
Classifier: License :: OSI Approved :: MIT License
Classifier: Operating System :: OS Independent
Requires-Python: >=3.6
